Metadata-Version: 1.1
Name: browserinfo
Version: 0.2.0
Summary: API wrapper for browser-info.net - retrieve UA strings
Home-page: https://github.com/stylesuxx/browserinfo
Author: Chris Landa
Author-email: stylesuxx@gmail.com
License: MIT
Download-URL: https://github.com/stylesuxx/browserinfo/tarball/0.2.0
Platform: UNKNOWN
Classifier: Programming Language :: Python
Classifier: Programming Language :: Python :: 2.7
Classifier: License :: OSI Approved :: MIT License
Classifier: Intended Audience :: Developers
Classifier: Operating System :: OS Independent
Classifier: Topic :: Software Development :: Libraries :: Python Modules
Classifier: Topic :: Internet :: WWW/HTTP
